farsakh/KMeansCoff_file.py
farsakh/__init__.py
farsakh/classification_metrics_file.py
farsakh/evaluate_classification_file.py
farsakh/evaluate_regression_file.py
farsakh/explore_categorical_file.py
farsakh/explore_numeric_file.py
farsakh/modelSearch_file.py
farsakh/neural_networks_builder_file.py
farsakh/overView_file.py
farsakh/plot_PCA_file.py
farsakh/plot_categorical_vs_target_file.py
farsakh/plot_history_file.py
farsakh/plot_numeric_vs_target_file.py
farsakh/preprocessor_maker_file.py
farsakh/regression_metrics_file.py
farsakh_df-0.1.8.dist-info/METADATA
farsakh_df-0.1.8.dist-info/WHEEL
farsakh_df-0.1.8.dist-info/top_level.txt
farsakh_df-0.1.8.dist-info/RECORD
