Metadata-Version: 2.1
Name: farsakh-df
Version: 0.1.8
Summary: Data Science
Author: Hamza Mohammed Farsakh
Author-email: <farsakh.m.hamza@gmail.com>
Keywords: python,sklearn
Classifier: Development Status :: 1 - Planning
Classifier: Intended Audience :: Developers
Classifier: Programming Language :: Python :: 3
Classifier: Operating System :: Unix
Classifier: Operating System :: MacOS :: MacOS X
Classifier: Operating System :: Microsoft :: Windows
